src/__init__.py
src/api.py
censusWrapper-0.0.1.dist-info/LICENSE
censusWrapper-0.0.1.dist-info/METADATA
censusWrapper-0.0.1.dist-info/WHEEL
censusWrapper-0.0.1.dist-info/top_level.txt
censusWrapper-0.0.1.dist-info/RECORD
