Metadata-Version: 2.1
Name: censusWrapper
Version: 0.0.1
Summary: A Python package for fetching and processing data from a Census API
Author: lennon0926
Author-email: <onnelle.lugo@upr.edu>
Keywords: python,api,request,census,data,pandas,wrapper
Classifier: Development Status :: 1 - Planning
Classifier: Intended Audience :: Developers
Classifier: Programming Language :: Python :: 3
Classifier: Operating System :: Unix
Classifier: Operating System :: MacOS :: MacOS X
Classifier: Operating System :: Microsoft :: Windows
License-File: LICENSE
Requires-Dist: requests
Requires-Dist: pandas
